pyrmute_registry/__init__.py
pyrmute_registry/_version.py
pyrmute_registry/client.py
pyrmute_registry/constants.py
pyrmute_registry/exceptions.py
pyrmute_registry/plugin.py
pyrmute_registry/py.typed
pyrmute_registry/types.py
pyrmute_registry/server/__init__.py
pyrmute_registry/server/auth.py
pyrmute_registry/server/cli.py
pyrmute_registry/server/config.py
pyrmute_registry/server/db.py
pyrmute_registry/server/deps.py
pyrmute_registry/server/main.py
pyrmute_registry/server/models/__init__.py
pyrmute_registry/server/models/schema.py
pyrmute_registry/server/routers/__init__.py
pyrmute_registry/server/routers/health.py
pyrmute_registry/server/routers/root.py
pyrmute_registry/server/routers/schemas.py
pyrmute_registry/server/schemas/__init__.py
pyrmute_registry/server/schemas/errors.py
pyrmute_registry/server/schemas/health.py
pyrmute_registry/server/schemas/root.py
pyrmute_registry/server/schemas/schema.py
pyrmute_registry/server/services/__init__.py
pyrmute_registry/server/services/schema.py
pyrmute_registry/server/utils/__init__.py
pyrmute_registry/server/utils/versioning.py
pyrmute_registry-0.0.1.dist-info/licenses/LICENSE
pyrmute_registry-0.0.1.dist-info/METADATA
pyrmute_registry-0.0.1.dist-info/WHEEL
pyrmute_registry-0.0.1.dist-info/entry_points.txt
pyrmute_registry-0.0.1.dist-info/top_level.txt
pyrmute_registry-0.0.1.dist-info/RECORD
