Metadata-Version: 2.4
Name: pyrmute-registry
Version: 0.0.1
Summary: Pyrmute Schema Registry
Author-email: Matt Ferrera <mattferrera@gmail.com>
License: MIT
Project-URL: Homepage, https://github.com/mferrera/pyrmute-registry
Project-URL: Repository, https://github.com/mferrera/pyrmute-registry
Project-URL: Documentation, https://github.com/mferrera/pyrmute-registry
Keywords: pydantic,versioning,schema,registry,jsonschema
Classifier: Development Status :: 3 - Alpha
Classifier: Topic :: Utilities
Classifier: Operating System :: POSIX :: Linux
Classifier: Programming Language :: Python :: 3.11
Classifier: Programming Language :: Python :: 3.12
Classifier: Programming Language :: Python :: 3.13
Classifier: Programming Language :: Python :: 3.14
Classifier: Natural Language :: English
Requires-Python: >=3.11
License-File: LICENSE
Requires-Dist: httpx
Requires-Dist: pydantic
Requires-Dist: pyrmute
Requires-Dist: tenacity
Dynamic: license-file
